conomy_api_client/__init__.py
conomy_api_client-0.0.9.6.dist-info/LICENSE
conomy_api_client-0.0.9.6.dist-info/METADATA
conomy_api_client-0.0.9.6.dist-info/WHEEL
conomy_api_client-0.0.9.6.dist-info/top_level.txt
conomy_api_client-0.0.9.6.dist-info/RECORD
