Metadata-Version: 2.1
Name: conomy-api-client
Version: 0.0.9.6
Summary: Client for access to "Conomy" microservices
Home-page: https://gitlab.conomy.net/suglobov/conomy-api-client.git
Author: Andrey Suglobov
Author-email: suglobov@conomy.ru
License: UNKNOWN
Platform: UNKNOWN
Classifier: Programming Language :: Python :: 3
Classifier: License :: OSI Approved :: MIT License
Classifier: Operating System :: OS Independent
Requires-Python: >=3.6
